MANIFEST.in
README.md
setup.py
client/powerline.c
client/powerline.py
client/powerline.sh
docs/Makefile
docs/source/commands.rst
docs/source/conf.py
docs/source/configuration.rst
docs/source/develop.rst
docs/source/index.rst
docs/source/installation.rst
docs/source/license-and-credits.rst
docs/source/overview.rst
docs/source/powerline_autodoc.py
docs/source/powerline_automan.py
docs/source/tips-and-tricks.rst
docs/source/troubleshooting.rst
docs/source/usage.rst
docs/source/commands/config.rst
docs/source/commands/daemon.rst
docs/source/commands/lint.rst
docs/source/commands/main.rst
docs/source/configuration/listers.rst
docs/source/configuration/local.rst
docs/source/configuration/reference.rst
docs/source/configuration/segments.rst
docs/source/configuration/selectors.rst
docs/source/configuration/segments/common.rst
docs/source/configuration/segments/i3wm.rst
docs/source/configuration/segments/pdb.rst
docs/source/configuration/segments/randr.rst
docs/source/configuration/segments/shell.rst
docs/source/configuration/segments/tmux.rst
docs/source/configuration/segments/vim.rst
docs/source/configuration/selectors/vim.rst
docs/source/develop/extensions.rst
docs/source/develop/listers.rst
docs/source/develop/local-themes.rst
docs/source/develop/segments.rst
docs/source/develop/tips-and-tricks.rst
docs/source/installation/linux.rst
docs/source/installation/osx.rst
docs/source/troubleshooting/linux.rst
docs/source/troubleshooting/osx.rst
docs/source/usage/other.rst
docs/source/usage/shell-prompts.rst
docs/source/usage/wm-widgets.rst
powerline/__init__.py
powerline/colorscheme.py
powerline/config.py
powerline/ipython.py
powerline/lemonbar.py
powerline/pdb.py
powerline/renderer.py
powerline/segment.py
powerline/shell.py
powerline/theme.py
powerline/vim.py
powerline/bindings/__init__.py
powerline/bindings/config.py
powerline/bindings/awesome/powerline-awesome.py
powerline/bindings/awesome/powerline.lua
powerline/bindings/bash/powerline.sh
powerline_status_i3.egg-info/PKG-INFO
powerline_status_i3.egg-info/SOURCES.txt
powerline_status_i3.egg-info/dependency_links.txt
powerline_status_i3.egg-info/not-zip-safe
powerline_status_i3.egg-info/requires.txt
powerline_status_i3.egg-info/top_level.txt
