Metadata-Version: 2.1
Name: powerline-status-i3
Version: 1.8.1
Summary: The ultimate statusline/prompt utility. A fork containing more features for the i3 window manager.
Home-page: https://github.com/ph111p/powerline
Author: Philip Wellnitz
Author-email: philipwellnitz@gmx.de
License: MIT
Download-URL: https://github.com/ph111p/powerline/archive/develop.zip
Platform: UNKNOWN
Classifier: Development Status :: 5 - Production/Stable
Classifier: Environment :: Console
Classifier: Environment :: Plugins
Classifier: Intended Audience :: End Users/Desktop
Classifier: License :: OSI Approved :: MIT License
Classifier: Natural Language :: English
Classifier: Operating System :: Microsoft :: Windows
Classifier: Operating System :: POSIX
Classifier: Programming Language :: Python :: 3.4
Classifier: Programming Language :: Python :: 3.5
Classifier: Programming Language :: Python :: 3.6
Classifier: Programming Language :: Python :: Implementation :: CPython
Classifier: Programming Language :: Python :: Implementation :: PyPy
Provides-Extra: wifi segment support
Provides-Extra: appoints segment support, Google Calendar
Provides-Extra: cpu load segment support
Provides-Extra: volume segment
Provides-Extra: docs
